setup.cfg
setup.py
rum.component.egg-info/PKG-INFO
rum.component.egg-info/SOURCES.txt
rum.component.egg-info/dependency_links.txt
rum.component.egg-info/entry_points.txt
rum.component.egg-info/not-zip-safe
rum.component.egg-info/requires.txt
rum.component.egg-info/top_level.txt
rumcomponent/__init__.py
rumcomponent/exceptions.py
rumcomponent/util.py
rumcomponent/tests/__init__.py
rumcomponent/tests/test_component.py