Metadata-Version: 1.0
Name: rum.component
Version: 0.0.1dev
Summary: Lightweight Component Architecture
Home-page: UNKNOWN
Author: Alberto Valverde, Michael Brickenstein
Author-email: brickenstein@mfo.de
License: MIT
Keywords: Component rum
Platform: UNKNOWN
Classifier: Development Status :: 3 - Alpha
